TRA/LM.py
TRA/PD.py
TRA/__init__.py
TRA-2.15.dist-info/LICENSE.txt
TRA-2.15.dist-info/METADATA
TRA-2.15.dist-info/WHEEL
TRA-2.15.dist-info/top_level.txt
TRA-2.15.dist-info/RECORD
