Metadata-Version: 2.1
Name: TRA
Version: 2.15
Summary: Trust region algorithms for non-linear optimisation.
Home-page: https://github.com/Joel-H-dot/TRA
Author: Joel Hampton
Author-email: joelelihampton@outlook.com
License: MIT
Keywords: non_linear optimisation
Platform: UNKNOWN
Classifier: Development Status :: 4 - Beta
Classifier: Intended Audience :: Science/Research 
Classifier: License :: OSI Approved :: MIT License
Classifier: Programming Language :: Python :: 3
Requires-Dist: numpy
